alphabet_soup_lambert-0.1.data/scripts/lambert_soup.py
answer_files/__init__.py
test_files/__init__.py
alphabet_soup_lambert-0.1.dist-info/METADATA
alphabet_soup_lambert-0.1.dist-info/WHEEL
alphabet_soup_lambert-0.1.dist-info/top_level.txt
alphabet_soup_lambert-0.1.dist-info/RECORD
