Metadata-Version: 2.1
Name: alphabet-soup-lambert
Version: 0.1
Summary: A word search project
Home-page: https://github.com/alambe13/alphabet-soup
Author: Angela Lambert
Author-email: alambe13@terpmail.umd.edu
License: UNKNOWN
Platform: UNKNOWN
Classifier: Programming Language :: Python :: 3
Classifier: License :: OSI Approved :: MIT License
Classifier: Operating System :: OS Independent
Requires-Python: >=2.7
